fibonacci_rattrapages/setup.py
fibonacci_rattrapages-0.0.1.dist-info/METADATA
fibonacci_rattrapages-0.0.1.dist-info/WHEEL
fibonacci_rattrapages-0.0.1.dist-info/top_level.txt
fibonacci_rattrapages-0.0.1.dist-info/RECORD
