Metadata-Version: 2.1
Name: fibonacci-rattrapages
Version: 0.0.1
Summary: Package that provides an implementation of fibonacci sequence
Home-page: https://github.com/mon-nom/mon-projet
Author: Mon Nom
Author-email: Your name <your.name@isen.yncrea.fr>
Classifier: Programming Language :: Python :: 3
Classifier: License :: OSI Approved :: MIT License
Classifier: Operating System :: OS Independent
Requires-Python: >=3.6
Requires-Dist: numpy (>=1.21.0)
Requires-Dist: pandas (>=1.3.0)
Requires-Dist: matplotlib (>=3.4.0)
